conformal_tights/__init__.py
conformal_tights/_coherent_linear_quantile_regressor.py
conformal_tights/_conformal_coherent_quantile_regressor.py
conformal_tights/_darts_forecaster.py
conformal_tights/_typing.py
conformal_tights/_validate_data.py
conformal_tights/py.typed
conformal_tights-0.4.1.dist-info/METADATA
conformal_tights-0.4.1.dist-info/WHEEL
conformal_tights-0.4.1.dist-info/licenses/LICENSE
conformal_tights-0.4.1.dist-info/RECORD
