Metadata-Version: 2.4
Name: conformal-tights
Version: 0.4.1
Summary: A Python package for Coherent Conformal Prediction.
Project-URL: homepage, https://github.com/superlinear-ai/conformal-tights
Project-URL: source, https://github.com/superlinear-ai/conformal-tights
Project-URL: changelog, https://github.com/superlinear-ai/conformal-tights/blob/main/CHANGELOG.md
Project-URL: releasenotes, https://github.com/superlinear-ai/conformal-tights/releases
Project-URL: documentation, https://github.com/superlinear-ai/conformal-tights
Project-URL: issues, https://github.com/superlinear-ai/conformal-tights/issues
Author-email: Laurent Sorber <laurent@superlinear.eu>
License-File: LICENSE
Requires-Python: <4.0,>=3.10
Requires-Dist: numpy>=1.26.0
Requires-Dist: pandas>=2.1.1
Requires-Dist: scikit-learn>=1.3.1
Requires-Dist: scipy!=1.15.0.*,!=1.15.1,!=1.15.2,>=1.11.2
Requires-Dist: u8darts>=0.28.0
Requires-Dist: xgboost>=2.1.0
